README.md
setup.py
chatwhy/__init__.py
chatwhy.egg-info/PKG-INFO
chatwhy.egg-info/SOURCES.txt
chatwhy.egg-info/dependency_links.txt
chatwhy.egg-info/not-zip-safe
chatwhy.egg-info/top_level.txt